trackify/__init__.py
trackify/backend_cli.py
trackify/tracker_cli.py
trackify/backend/requirements.txt
trackify/backend/config/categories.json
trackify_pc-1.0.2.dist-info/licenses/LICENSE
trackify_pc-1.0.2.dist-info/METADATA
trackify_pc-1.0.2.dist-info/WHEEL
trackify_pc-1.0.2.dist-info/entry_points.txt
trackify_pc-1.0.2.dist-info/top_level.txt
trackify_pc-1.0.2.dist-info/RECORD
