Metadata-Version: 2.4
Name: trackify-pc
Version: 1.0.2
Summary: A comprehensive PC activity tracking and productivity analysis system
Home-page: https://github.com/yourusername/trackify
Author: Your Name
Author-email: Your Name <your.email@example.com>
Maintainer-email: Your Name <your.email@example.com>
License-Expression: MIT
Project-URL: Homepage, https://github.com/yourusername/trackify
Project-URL: Documentation, https://github.com/yourusername/trackify#readme
Project-URL: Repository, https://github.com/yourusername/trackify
Project-URL: Bug Tracker, https://github.com/yourusername/trackify/issues
Keywords: activity,tracking,productivity,time-management,windows,monitoring
Classifier: Development Status :: 4 - Beta
Classifier: Intended Audience :: End Users/Desktop
Classifier: Topic :: Office/Business :: Scheduling
Classifier: Programming Language :: Python :: 3
Classifier: Programming Language :: Python :: 3.8
Classifier: Programming Language :: Python :: 3.9
Classifier: Programming Language :: Python :: 3.10
Classifier: Programming Language :: Python :: 3.11
Classifier: Programming Language :: Python :: 3.12
Classifier: Programming Language :: Python :: 3.13
Classifier: Operating System :: Microsoft :: Windows
Requires-Python: >=3.8
License-File: LICENSE
Requires-Dist: fastapi>=0.115.0
Requires-Dist: uvicorn[standard]>=0.32.0
Requires-Dist: sqlalchemy>=2.0.36
Requires-Dist: python-multipart>=0.0.20
Requires-Dist: pydantic>=2.10.0
Requires-Dist: psutil>=6.1.0
Requires-Dist: pywin32>=307
Requires-Dist: aiofiles>=23.0.0
Provides-Extra: dev
Requires-Dist: pytest>=7.0.0; extra == "dev"
Requires-Dist: pytest-cov>=4.0.0; extra == "dev"
Requires-Dist: black>=23.0.0; extra == "dev"
Requires-Dist: flake8>=6.0.0; extra == "dev"
Requires-Dist: mypy>=1.0.0; extra == "dev"
Dynamic: author
Dynamic: home-page
Dynamic: license-file
Dynamic: requires-python
